uncompressor/__init__.py
uncompressor/compressed.py
uncompressor/main.py
uncompressor/uncompress.py
uncompressor-0.1.0.dist-info/entry_points.txt
uncompressor-0.1.0.dist-info/WHEEL
uncompressor-0.1.0.dist-info/METADATA
uncompressor-0.1.0.dist-info/RECORD
