Metadata-Version: 2.1
Name: uncompressor
Version: 0.1.0
Summary: easy file uncompressor.
License: MIT
Author: Hibiki Okada
Author-email: 4617016@ed.tus.ac.jp
Requires-Python: >=3.8,<4.0
Classifier: License :: OSI Approved :: MIT License
Classifier: Programming Language :: Python :: 3
Classifier: Programming Language :: Python :: 3.8
Requires-Dist: Click (>=7.1.2,<8.0.0)
